prc/__init__.py
prc/client.py
prc/exceptions.py
prc/server.py
prc/webhooks.py
prc/api_types/__init__.py
prc/api_types/v1.py
prc/models/__init__.py
prc/models/commands.py
prc/models/player.py
prc/models/webhooks.py
prc/models/server/__init__.py
prc/models/server/logs.py
prc/models/server/player.py
prc/models/server/staff.py
prc/models/server/status.py
prc/models/server/vehicle.py
prc/utility/__init__.py
prc/utility/cache.py
prc/utility/enum.py
prc/utility/requests.py
prc_api-0.16.0.dist-info/licenses/LICENSE
prc_api-0.16.0.dist-info/METADATA
prc_api-0.16.0.dist-info/WHEEL
prc_api-0.16.0.dist-info/top_level.txt
prc_api-0.16.0.dist-info/RECORD
