Metadata-Version: 2.4
Name: prc.api
Version: 0.16.0
Summary: prc.api is an asynchronous Python wrapper for the PRC/ERLC API
Home-page: https://github.com/TychoTeam/prc.api-py
Author: Tycho
Author-email: mail@tycho.team
License: MIT
Keywords: erlc,ER:LC,prc,PRC API
Classifier: Framework :: AsyncIO
Requires-Python: >=3.8
License-File: LICENSE
Requires-Dist: httpx
Requires-Dist: asyncio
Dynamic: author
Dynamic: author-email
Dynamic: classifier
Dynamic: description
Dynamic: description-content-type
Dynamic: home-page
Dynamic: keywords
Dynamic: license
Dynamic: license-file
Dynamic: requires-dist
Dynamic: requires-python
Dynamic: summary
